{
    "key": "group_5edd4aea6da65",
    "title": "Listings Block",
    "fields": [
        {
            "key": "field_5f0c1c43f892a",
            "label": "Listing Block Category",
            "name": "listing_block_category",
            "type": "select",
            "instructions": "",
            "required": 0,
            "conditional_logic": 0,
            "wrapper": {
                "width": "",
                "class": "",
                "id": ""
            },
            "choices": {
                "events": "Events",
                "retail": "Retail",
                "games": "Games"
            },
            "default_value": false,
            "allow_null": 0,
            "multiple": 0,
            "ui": 1,
            "ajax": 0,
            "return_format": "value",
            "placeholder": ""
        },
        {
            "key": "field_5edd4c2f16171",
            "label": "Listing Block Heading",
            "name": "listing_block_heading",
            "type": "text",
            "instructions": "",
            "required": 0,
            "conditional_logic": 0,
            "wrapper": {
                "width": "",
                "class": "",
                "id": ""
            },
            "default_value": "",
            "placeholder": "",
            "prepend": "",
            "append": "",
            "maxlength": ""
        },
        {
            "key": "field_5f0f9ff5aa06d",
            "label": "Initial Search",
            "name": "initial_search",
            "type": "group",
            "instructions": "",
            "required": 0,
            "conditional_logic": 0,
            "wrapper": {
                "width": "",
                "class": "",
                "id": ""
            },
            "layout": "block",
            "sub_fields": [
                {
                    "key": "field_5f0fa005aa06e",
                    "label": "Search Type",
                    "name": "search_type",
                    "type": "select",
                    "instructions": "",
                    "required": 0,
                    "conditional_logic": 0,
                    "wrapper": {
                        "width": "40",
                        "class": "",
                        "id": ""
                    },
                    "choices": {
                        "query": "Query",
                        "location": "Location"
                    },
                    "default_value": false,
                    "allow_null": 0,
                    "multiple": 0,
                    "ui": 1,
                    "ajax": 0,
                    "return_format": "value",
                    "placeholder": ""
                },
                {
                    "key": "field_5f0fa025aa06f",
                    "label": "Search Value",
                    "name": "search_value",
                    "type": "text",
                    "instructions": "",
                    "required": 0,
                    "conditional_logic": 0,
                    "wrapper": {
                        "width": "60",
                        "class": "",
                        "id": ""
                    },
                    "default_value": "",
                    "placeholder": "",
                    "prepend": "",
                    "append": "",
                    "maxlength": ""
                }
            ]
        },
        {
            "key": "field_5ee254ba8ac14",
            "label": "Show Filters?",
            "name": "show_filters",
            "type": "true_false",
            "instructions": "",
            "required": 0,
            "conditional_logic": 0,
            "wrapper": {
                "width": "30",
                "class": "",
                "id": ""
            },
            "message": "",
            "default_value": 0,
            "ui": 1,
            "ui_on_text": "",
            "ui_off_text": ""
        },
        {
            "key": "field_5f2cb2c5e0350",
            "label": "Load More Type",
            "name": "load_more_type",
            "type": "radio",
            "instructions": "",
            "required": 0,
            "conditional_logic": 0,
            "wrapper": {
                "width": "70",
                "class": "",
                "id": ""
            },
            "choices": {
                "pagination": "Pagination",
                "infinite_scroll": "Infinite Scroll"
            },
            "allow_null": 0,
            "other_choice": 0,
            "default_value": "pagination",
            "layout": "horizontal",
            "return_format": "value",
            "save_other_choice": 0
        },
        {
            "key": "field_5ee2549d8ac13",
            "label": "Filters",
            "name": "",
            "type": "tab",
            "instructions": "",
            "required": 0,
            "conditional_logic": 0,
            "wrapper": {
                "width": "",
                "class": "",
                "id": ""
            },
            "placement": "top",
            "endpoint": 0
        },
        {
            "key": "field_5f0c5fd9322d8",
            "label": "Filters",
            "name": "filters",
            "type": "group",
            "instructions": "",
            "required": 0,
            "conditional_logic": 0,
            "wrapper": {
                "width": "",
                "class": "",
                "id": ""
            },
            "layout": "block",
            "sub_fields": [
                {
                    "key": "field_5f0c21796269b",
                    "label": "Filter Heading",
                    "name": "filter_heading",
                    "type": "text",
                    "instructions": "",
                    "required": 0,
                    "conditional_logic": 0,
                    "wrapper": {
                        "width": "",
                        "class": "",
                        "id": ""
                    },
                    "default_value": "",
                    "placeholder": "",
                    "prepend": "",
                    "append": "",
                    "maxlength": ""
                },
                {
                    "key": "field_5edf2188c7861",
                    "label": "Filters",
                    "name": "listings_filters",
                    "type": "repeater",
                    "instructions": "",
                    "required": 0,
                    "conditional_logic": 0,
                    "wrapper": {
                        "width": "",
                        "class": "",
                        "id": ""
                    },
                    "collapsed": "",
                    "min": 0,
                    "max": 0,
                    "layout": "block",
                    "button_label": "",
                    "sub_fields": [
                        {
                            "key": "field_5edfbf527baaf",
                            "label": "Type",
                            "name": "type",
                            "type": "select",
                            "instructions": "",
                            "required": 0,
                            "conditional_logic": 0,
                            "wrapper": {
                                "width": "20",
                                "class": "",
                                "id": ""
                            },
                            "choices": {
                                "date": "Date",
                                "text": "Text",
                                "list": "List"
                            },
                            "default_value": false,
                            "allow_null": 0,
                            "multiple": 0,
                            "ui": 0,
                            "return_format": "value",
                            "ajax": 0,
                            "placeholder": ""
                        },
                        {
                            "key": "field_5ee14c1441545",
                            "label": "Name",
                            "name": "name",
                            "type": "text",
                            "instructions": "",
                            "required": 0,
                            "conditional_logic": 0,
                            "wrapper": {
                                "width": "40",
                                "class": "",
                                "id": ""
                            },
                            "default_value": "",
                            "placeholder": "",
                            "prepend": "",
                            "append": "",
                            "maxlength": ""
                        },
                        {
                            "key": "field_5edfc1ac7bab0",
                            "label": "Label",
                            "name": "label",
                            "type": "text",
                            "instructions": "",
                            "required": 0,
                            "conditional_logic": 0,
                            "wrapper": {
                                "width": "40",
                                "class": "",
                                "id": ""
                            },
                            "default_value": "",
                            "placeholder": "",
                            "prepend": "",
                            "append": "",
                            "maxlength": ""
                        },
                        {
                            "key": "field_5ee2d0244b62b",
                            "label": "List Source",
                            "name": "list_source",
                            "type": "select",
                            "instructions": "",
                            "required": 0,
                            "conditional_logic": [
                                [
                                    {
                                        "field": "field_5edfbf527baaf",
                                        "operator": "==",
                                        "value": "list"
                                    }
                                ]
                            ],
                            "wrapper": {
                                "width": "30",
                                "class": "",
                                "id": ""
                            },
                            "choices": {
                                "wordpress": "Wordpress",
                                "api": "Api"
                            },
                            "default_value": "wordpress",
                            "allow_null": 0,
                            "multiple": 0,
                            "ui": 1,
                            "ajax": 0,
                            "return_format": "value",
                            "placeholder": ""
                        },
                        {
                            "key": "field_5ee163f0ec969",
                            "label": "Select List",
                            "name": "list",
                            "type": "post_object",
                            "instructions": "",
                            "required": 0,
                            "conditional_logic": [
                                [
                                    {
                                        "field": "field_5edfbf527baaf",
                                        "operator": "==",
                                        "value": "list"
                                    },
                                    {
                                        "field": "field_5ee2d0244b62b",
                                        "operator": "==",
                                        "value": "wordpress"
                                    }
                                ]
                            ],
                            "wrapper": {
                                "width": "70",
                                "class": "",
                                "id": ""
                            },
                            "post_type": [
                                "lists_post_type"
                            ],
                            "taxonomy": "",
                            "allow_null": 0,
                            "multiple": 0,
                            "return_format": "object",
                            "ui": 1
                        },
                        {
                            "key": "field_5ee2d0a94b62d",
                            "label": "Api Endpoint",
                            "name": "api_endpoint",
                            "type": "text",
                            "instructions": "",
                            "required": 0,
                            "conditional_logic": [
                                [
                                    {
                                        "field": "field_5edfbf527baaf",
                                        "operator": "==",
                                        "value": "list"
                                    },
                                    {
                                        "field": "field_5ee2d0244b62b",
                                        "operator": "==",
                                        "value": "api"
                                    }
                                ]
                            ],
                            "wrapper": {
                                "width": "70",
                                "class": "",
                                "id": ""
                            },
                            "default_value": "",
                            "placeholder": "",
                            "prepend": "",
                            "append": "",
                            "maxlength": ""
                        }
                    ]
                }
            ]
        }
    ],
    "location": [
        [
            {
                "param": "block",
                "operator": "==",
                "value": "acf\/tru-fetcher-listings"
            }
        ]
    ],
    "menu_order": 0,
    "position": "side",
    "style": "default",
    "label_placement": "top",
    "instruction_placement": "label",
    "hide_on_screen": "",
    "active": 1,
    "description": "",
    "modified": 1597167394
}